odoo/addons/so_product_set_report_hide_lines/README.rst
odoo/addons/so_product_set_report_hide_lines/__init__.py
odoo/addons/so_product_set_report_hide_lines/__manifest__.py
odoo/addons/so_product_set_report_hide_lines/i18n/es.po
odoo/addons/so_product_set_report_hide_lines/models/__init__.py
odoo/addons/so_product_set_report_hide_lines/models/product_set_line.py
odoo/addons/so_product_set_report_hide_lines/static/description/icon.png
odoo/addons/so_product_set_report_hide_lines/views/product_set.xml
odoo/addons/so_product_set_report_hide_lines/wizard/__init__.py
odoo/addons/so_product_set_report_hide_lines/wizard/product_set_add.py
odoo/addons/so_product_set_report_hide_lines/wizard/product_set_add.xml
odoo_addon_so_product_set_report_hide_lines-15.0.1.0.0.3.dist-info/METADATA
odoo_addon_so_product_set_report_hide_lines-15.0.1.0.0.3.dist-info/WHEEL
odoo_addon_so_product_set_report_hide_lines-15.0.1.0.0.3.dist-info/top_level.txt
odoo_addon_so_product_set_report_hide_lines-15.0.1.0.0.3.dist-info/RECORD
