Metadata-Version: 2.1
Name: odoo-addon-so_product_set_report_hide_lines
Version: 15.0.1.0.0.3
Requires-Python: >=3.8
Requires-Dist: odoo-addon-sale_product_set>=15.0dev,<15.1dev
Requires-Dist: odoo-addon-so_report_hide_lines>=15.0dev,<15.1dev
Requires-Dist: odoo>=15.0a,<15.1dev
Summary: Hide sale order lines by product set
Home-page: https://github.com/sygel-technology/sy-sale-reporting
License: AGPL-3
Author: Sygel, Odoo Community Association (OCA)
Author-email: support@odoo-community.org
Classifier: Programming Language :: Python
Classifier: Framework :: Odoo
Classifier: Framework :: Odoo :: 15.0
Classifier: License :: OSI Approved :: GNU Affero General Public License v3
